{"instances":[{"type":"bbox","classId":1,"probability":100,"points":{"x1":0,"x2":1280,"y1":0,"y2":311.29998779296875},"groupId":0,"pointLabels":{},"locked":false,"visible":true,"attributes":[]},{"type":"bbox","classId":1,"probability":100,"points":{"x1":0,"x2":472.20001220703125,"y1":418.9370422363281,"y2":720},"groupId":0,"pointLabels":{},"locked":false,"visible":true,"attributes":[]},{"type":"bbox","classId":1,"probability":100,"points":{"x1":0,"x2":1280,"y1":417.6559143066406,"y2":589.2999877929688},"groupId":0,"pointLabels":{},"locked":false,"visible":true,"attributes":[]},{"type":"bbox","classId":1,"probability":100,"points":{"x1":719.447509765625,"x2":1280,"y1":7.105427357601002e-15,"y2":591.9000244140625},"groupId":0,"pointLabels":{},"locked":false,"visible":true,"attributes":[]}],"tags":[],"metadata":{"version":"1.0.0","name":"040_(130).jpg","status":"Completed"}}