{"instances":[{"type":"bbox","classId":1,"probability":100,"points":{"x1":0,"x2":1280,"y1":0,"y2":298.5},"groupId":0,"pointLabels":{},"locked":false,"visible":true,"attributes":[]},{"type":"bbox","classId":1,"probability":100,"points":{"x1":0,"x2":827.0999755859375,"y1":418.9,"y2":623.9},"groupId":0,"pointLabels":{},"locked":false,"visible":true,"attributes":[]},{"type":"bbox","classId":1,"probability":100,"points":{"x1":828.3455200195312,"x2":1280,"y1":298.5086669921875,"y2":625.2000122070312},"groupId":0,"pointLabels":{},"locked":false,"visible":true,"attributes":[]}],"tags":[],"metadata":{"version":"1.0.0","name":"040_(221).jpg","status":"Completed"}}